{
  "id": "shakespeare",
  "name": "William Shakespeare",
  "subtitle": "The Bard of Avon",
  "portrait": "🎭",
  "bio": "English playwright and poet, widely regarded as the greatest writer in the English language.",
  "works": [
    {
      "id": "to-be-or-not-to-be",
      "title": "To be, or not to be",
      "source": "Hamlet",
      "character": "Hamlet",
      "act": "Act 3, Scene 1",
      "chunks": [
        {
          "front": "To be, or not to be,",
          "back": "that is the question:"
        },
        {
          "front": "Whether 'tis nobler in the mind",
          "back": "to suffer"
        },
        {
          "front": "The slings and arrows",
          "back": "of outrageous fortune,"
        },
        {
          "front": "Or to take arms against",
          "back": "a sea of troubles"
        },
        {
          "front": "And by opposing",
          "back": "end them."
        },
        {
          "front": "To die—to sleep,",
          "back": "No more;"
        },
        {
          "front": "and by a sleep to say we end",
          "back": "The heart-ache and the thousand natural shocks"
        },
        {
          "front": "That flesh is heir to:",
          "back": "'tis a consummation"
        },
        {
          "front": "Devoutly",
          "back": "to be wish'd."
        },
        {
          "front": "To die, to sleep; To sleep,",
          "back": "perchance to dream—"
        },
        {
          "front": "ay, there's",
          "back": "the rub:"
        },
        {
          "front": "For in that sleep of death",
          "back": "what dreams may come,"
        },
        {
          "front": "When we have shuffled off",
          "back": "this mortal coil,"
        },
        {
          "front": "Must give us pause—",
          "back": "there's the respect"
        },
        {
          "front": "That makes calamity",
          "back": "of so long life."
        },
        {
          "front": "For who would bear the whips",
          "back": "and scorns of time,"
        },
        {
          "front": "Th' oppressor's wrong,",
          "back": "the proud man's contumely,"
        },
        {
          "front": "The pangs of despis'd love,",
          "back": "the law's delay,"
        },
        {
          "front": "The insolence of office, and",
          "back": "the spurns"
        },
        {
          "front": "That patient merit of",
          "back": "th' unworthy takes,"
        },
        {
          "front": "When he himself might",
          "back": "his quietus make"
        },
        {
          "front": "With a bare bodkin? Who would",
          "back": "fardels bear,"
        },
        {
          "front": "To grunt and sweat under",
          "back": "a weary life,"
        },
        {
          "front": "But that the dread of something",
          "back": "after death,"
        },
        {
          "front": "The undiscover'd country, from",
          "back": "whose bourn"
        },
        {
          "front": "No traveller returns,",
          "back": "puzzles the will,"
        },
        {
          "front": "And makes us rather bear",
          "back": "those ills we have"
        },
        {
          "front": "Than fly to others",
          "back": "that we know not of?"
        },
        {
          "front": "Thus conscience does make",
          "back": "cowards of us all,"
        },
        {
          "front": "And thus the native hue",
          "back": "of resolution"
        },
        {
          "front": "Is sicklied o'er with the",
          "back": "pale cast of thought,"
        },
        {
          "front": "And enterprises of great",
          "back": "pitch and moment,"
        },
        {
          "front": "With this regard their currents",
          "back": "turn awry"
        },
        {
          "front": "And lose the name",
          "back": "of action."
        }
      ]
    },
    {
      "id": "tomorrow-and-tomorrow",
      "title": "Tomorrow, and tomorrow, and tomorrow",
      "source": "Macbeth",
      "character": "Macbeth",
      "act": "Act 5, Scene 5",
      "chunks": [
        {
          "front": "Tomorrow, and tomorrow,",
          "back": "and tomorrow,"
        },
        {
          "front": "Creeps in this petty pace",
          "back": "from day to day,"
        },
        {
          "front": "To the last syllable",
          "back": "of recorded time;"
        },
        {
          "front": "And all our yesterdays have",
          "back": "lighted fools"
        },
        {
          "front": "The way to",
          "back": "dusty death."
        },
        {
          "front": "Out, out,",
          "back": "brief candle!"
        },
        {
          "front": "Life's but a walking shadow,",
          "back": "a poor player,"
        },
        {
          "front": "That struts and frets his hour",
          "back": "upon the stage,"
        },
        {
          "front": "And then",
          "back": "is heard no more."
        },
        {
          "front": "It is a tale told",
          "back": "by an idiot,"
        },
        {
          "front": "Full of sound and fury,",
          "back": "Signifying nothing."
        }
      ]
    },
    {
      "id": "is-this-a-dagger",
      "title": "Is this a dagger which I see before me",
      "source": "Macbeth",
      "character": "Macbeth",
      "act": "Act 2, Scene 1",
      "chunks": [
        {
          "front": "Is this a dagger",
          "back": "which I see before me,"
        },
        {
          "front": "The handle",
          "back": "toward my hand?"
        },
        {
          "front": "Come, let me",
          "back": "clutch thee:"
        },
        {
          "front": "I have thee not,",
          "back": "and yet I see thee still."
        },
        {
          "front": "Art thou not, fatal vision,",
          "back": "sensible to feeling as to sight?"
        },
        {
          "front": "Or art thou but a dagger",
          "back": "of the mind,"
        },
        {
          "front": "A false creation, proceeding from",
          "back": "the heat-oppressèd brain?"
        },
        {
          "front": "I see thee yet, in form",
          "back": "as palpable"
        },
        {
          "front": "As this which",
          "back": "now I draw."
        },
        {
          "front": "Thou marshall'st me the way",
          "back": "that I was going,"
        },
        {
          "front": "And such an instrument",
          "back": "I was to use."
        },
        {
          "front": "Mine eyes are made the fools",
          "back": "o' th' other senses,"
        },
        {
          "front": "Or else worth all",
          "back": "the rest."
        },
        {
          "front": "I see thee still, and on thy blade",
          "back": "and dudgeon gouts of blood,"
        },
        {
          "front": "Which was not",
          "back": "so before."
        },
        {
          "front": "There's no such thing:",
          "back": "It is the bloody business"
        },
        {
          "front": "which informs thus",
          "back": "to mine eyes."
        },
        {
          "front": "Now o'er the one half-world",
          "back": "Nature seems dead,"
        },
        {
          "front": "and wicked dreams abuse",
          "back": "The curtain'd sleep."
        },
        {
          "front": "Witchcraft celebrates pale",
          "back": "Hecate's offerings,"
        },
        {
          "front": "and wither'd murder, alarum'd",
          "back": "by his sentinel, the wolf,"
        },
        {
          "front": "Whose howl's his watch,",
          "back": "thus with his stealthy pace,"
        },
        {
          "front": "With Tarquin's ravishing strides,",
          "back": "towards his design"
        },
        {
          "front": "Moves like a ghost.",
          "back": "Thou sure and firm-set earth,"
        },
        {
          "front": "Hear not my steps,",
          "back": "which way they walk,"
        },
        {
          "front": "for fear thy very stones prate",
          "back": "of my whereabout,"
        },
        {
          "front": "And take the present horror",
          "back": "from the time,"
        },
        {
          "front": "Which now suits with it.",
          "back": "Whiles I threat, he lives:"
        },
        {
          "front": "Words to the heat of deeds",
          "back": "too cold breath gives."
        },
        {
          "front": "I go, and it is done;",
          "back": "the bell invites me."
        },
        {
          "front": "Hear it not, Duncan;",
          "back": "for it is a knell"
        },
        {
          "front": "That summons thee to heaven",
          "back": "or to hell."
        }
      ]
    },
    {
      "id": "all-the-worlds-a-stage",
      "title": "All the world's a stage",
      "source": "As You Like It",
      "character": "Jaques",
      "act": "Act 2, Scene 7",
      "chunks": [
        {
          "front": "All the world's",
          "back": "a stage,"
        },
        {
          "front": "And all the men and women",
          "back": "merely players;"
        },
        {
          "front": "They have their exits",
          "back": "and their entrances,"
        },
        {
          "front": "And one man in his time",
          "back": "plays many parts,"
        },
        {
          "front": "His acts being",
          "back": "seven ages."
        },
        {
          "front": "At first, the infant,",
          "back": "Mewling and puking in the nurse's arms."
        },
        {
          "front": "Then the whining schoolboy,",
          "back": "with his satchel"
        },
        {
          "front": "And shining morning face,",
          "back": "creeping like snail"
        },
        {
          "front": "Unwillingly",
          "back": "to school."
        },
        {
          "front": "And then the lover,",
          "back": "Sighing like furnace,"
        },
        {
          "front": "with a woeful ballad",
          "back": "Made to his mistress' eyebrow."
        },
        {
          "front": "Then a soldier, full of",
          "back": "strange oaths"
        },
        {
          "front": "and bearded like",
          "back": "the pard,"
        },
        {
          "front": "Jealous in honour, sudden",
          "back": "and quick in quarrel,"
        },
        {
          "front": "Seeking the bubble reputation",
          "back": "Even in the cannon's mouth."
        },
        {
          "front": "And then the justice,",
          "back": "In fair round belly with good capon lined,"
        },
        {
          "front": "With eyes severe and beard",
          "back": "of formal cut,"
        },
        {
          "front": "Full of wise saws and",
          "back": "modern instances;"
        },
        {
          "front": "And so he plays",
          "back": "his part."
        },
        {
          "front": "The sixth age shifts into",
          "back": "the lean and slippered pantaloon,"
        },
        {
          "front": "With spectacles on nose",
          "back": "and pouch on side;"
        },
        {
          "front": "His youthful hose, well saved,",
          "back": "a world too wide"
        },
        {
          "front": "For his shrunk shank,",
          "back": "and his big manly voice,"
        },
        {
          "front": "Turning again toward",
          "back": "childish treble, pipes"
        },
        {
          "front": "And whistles in",
          "back": "his sound."
        },
        {
          "front": "Last scene of all, that ends",
          "back": "this strange eventful history,"
        },
        {
          "front": "Is second childishness",
          "back": "and mere oblivion,"
        },
        {
          "front": "Sans teeth, sans eyes,",
          "back": "sans taste, sans everything."
        }
      ]
    },
    {
      "id": "now-is-the-winter",
      "title": "Now is the winter of our discontent",
      "source": "Richard III",
      "character": "Richard",
      "act": "Act 1, Scene 1",
      "chunks": [
        {
          "front": "Now is the winter",
          "back": "of our discontent"
        },
        {
          "front": "Made glorious summer",
          "back": "by this sun of York;"
        },
        {
          "front": "And all the clouds that lour'd",
          "back": "upon our house"
        },
        {
          "front": "In the deep bosom",
          "back": "of the ocean buried."
        },
        {
          "front": "Now are our brows bound",
          "back": "with victorious wreaths;"
        },
        {
          "front": "Our bruised arms hung up",
          "back": "for monuments;"
        },
        {
          "front": "Our stern alarums changed",
          "back": "to merry meetings,"
        },
        {
          "front": "Our dreadful marches",
          "back": "to delightful measures."
        },
        {
          "front": "Grim-visaged war hath",
          "back": "smooth'd his wrinkled front;"
        },
        {
          "front": "And now, instead of mounting",
          "back": "barbèd steeds"
        },
        {
          "front": "To fright the souls",
          "back": "of fearful adversaries,"
        },
        {
          "front": "He capers nimbly in",
          "back": "a lady's chamber"
        },
        {
          "front": "To the lascivious pleasing",
          "back": "of a lute."
        },
        {
          "front": "But I, that am not shaped",
          "back": "for sportive tricks,"
        },
        {
          "front": "Nor made to court an",
          "back": "amorous looking-glass;"
        },
        {
          "front": "I, that am rudely stamp'd,",
          "back": "and want love's majesty"
        },
        {
          "front": "To strut before a wanton",
          "back": "ambling nymph;"
        },
        {
          "front": "I, that am curtail'd of",
          "back": "this fair proportion,"
        },
        {
          "front": "Cheated of feature by",
          "back": "dissembling nature,"
        },
        {
          "front": "Deformed, unfinish'd,",
          "back": "sent before my time"
        },
        {
          "front": "Into this breathing world,",
          "back": "scarce half made up,"
        },
        {
          "front": "And that so lamely and",
          "back": "unfashionable"
        },
        {
          "front": "That dogs bark at me",
          "back": "as I halt by them;"
        },
        {
          "front": "Why, I, in this weak",
          "back": "piping time of peace,"
        },
        {
          "front": "Have no delight to pass",
          "back": "away the time,"
        },
        {
          "front": "Unless to spy my shadow",
          "back": "in the sun"
        },
        {
          "front": "And descant on mine own",
          "back": "deformity:"
        },
        {
          "front": "And therefore, since I cannot",
          "back": "prove a lover,"
        },
        {
          "front": "To entertain these fair",
          "back": "well-spoken days,"
        },
        {
          "front": "I am determined to",
          "back": "prove a villain"
        },
        {
          "front": "And hate the idle pleasures",
          "back": "of these days."
        }
      ]
    },
    {
      "id": "once-more-unto-the-breach",
      "title": "Once more unto the breach",
      "source": "Henry V",
      "character": "King Henry",
      "act": "Act 3, Scene 1",
      "chunks": [
        {
          "front": "Once more unto",
          "back": "the breach, dear friends,"
        },
        {
          "front": "once more; Or close the wall up",
          "back": "with our English dead."
        },
        {
          "front": "In peace there's nothing",
          "back": "so becomes a man"
        },
        {
          "front": "As modest stillness",
          "back": "and humility:"
        },
        {
          "front": "But when the blast of war",
          "back": "blows in our ears,"
        },
        {
          "front": "Then imitate the action",
          "back": "of the tiger;"
        },
        {
          "front": "Stiffen the sinews,",
          "back": "summon up the blood,"
        },
        {
          "front": "Disguise fair nature with",
          "back": "hard-favour'd rage;"
        },
        {
          "front": "Then lend the eye",
          "back": "a terrible aspect;"
        },
        {
          "front": "Let it pry through the portage",
          "back": "of the head"
        },
        {
          "front": "Like the brass cannon;",
          "back": "let the brow o'erwhelm it"
        },
        {
          "front": "As fearfully as doth a galled rock",
          "back": "O'erhang and jutty his confounded base,"
        },
        {
          "front": "Swill'd with the wild",
          "back": "and wasteful ocean."
        },
        {
          "front": "Now set the teeth and",
          "back": "stretch the nostril wide,"
        },
        {
          "front": "Hold hard the breath and",
          "back": "bend up every spirit"
        },
        {
          "front": "To his full height.",
          "back": "On, on, you noblest English,"
        },
        {
          "front": "Whose blood is fet from fathers",
          "back": "of war-proof!"
        },
        {
          "front": "Fathers that, like so many Alexanders,",
          "back": "Have in these parts from morn till even fought"
        },
        {
          "front": "And sheathed their swords",
          "back": "for lack of argument."
        },
        {
          "front": "Dishonour not your mothers;",
          "back": "now attest"
        },
        {
          "front": "That those whom you call'd fathers",
          "back": "did beget you."
        },
        {
          "front": "Be copy now to men",
          "back": "of grosser blood,"
        },
        {
          "front": "And teach them how",
          "back": "to war."
        },
        {
          "front": "And you, good yeoman, whose limbs",
          "back": "were made in England,"
        },
        {
          "front": "Show us here the mettle",
          "back": "of your pasture;"
        },
        {
          "front": "Let us swear that you are worth",
          "back": "your breeding;"
        },
        {
          "front": "Which I doubt not; for there is none of you",
          "back": "so mean and base,"
        },
        {
          "front": "That hath not noble lustre",
          "back": "in your eyes."
        },
        {
          "front": "I see you stand like greyhounds",
          "back": "in the slips,"
        },
        {
          "front": "Straining upon the start.",
          "back": "The game's afoot:"
        },
        {
          "front": "Follow your spirit, and upon this charge",
          "back": "Cry 'God for Harry, England, and Saint George!'"
        }
      ]
    },
    {
      "id": "this-royal-throne",
      "title": "This royal throne of kings",
      "source": "Richard II",
      "character": "John of Gaunt",
      "act": "Act 2, Scene 1",
      "chunks": [
        {
          "front": "This royal throne of kings,",
          "back": "this sceptred isle,"
        },
        {
          "front": "This earth of majesty,",
          "back": "this seat of Mars,"
        },
        {
          "front": "This other Eden,",
          "back": "demi-paradise,"
        },
        {
          "front": "This fortress built by Nature",
          "back": "for herself"
        },
        {
          "front": "Against infection and",
          "back": "the hand of war,"
        },
        {
          "front": "This happy breed",
          "back": "of men, this little world,"
        },
        {
          "front": "This precious stone set",
          "back": "in the silver sea,"
        },
        {
          "front": "Which serves it in the office",
          "back": "of a wall,"
        },
        {
          "front": "Or as a moat defensive",
          "back": "to a house,"
        },
        {
          "front": "Against the envy of",
          "back": "less happier lands,"
        },
        {
          "front": "This blessed plot, this earth,",
          "back": "this realm, this England."
        }
      ]
    },
    {
      "id": "o-what-a-rogue",
      "title": "O, what a rogue and peasant slave am I",
      "source": "Hamlet",
      "character": "Hamlet",
      "act": "Act 2, Scene 2",
      "chunks": [
        {
          "front": "O, what a rogue and",
          "back": "peasant slave am I!"
        },
        {
          "front": "Is it not monstrous that this player here,",
          "back": "But in a fiction, in a dream of passion,"
        },
        {
          "front": "Could force his soul so",
          "back": "to his own conceit"
        },
        {
          "front": "That from her working all",
          "back": "his visage wann'd,"
        },
        {
          "front": "Tears in his eyes, distraction",
          "back": "in's aspect,"
        },
        {
          "front": "A broken voice, and his whole function",
          "back": "suiting"
        },
        {
          "front": "With forms to",
          "back": "his conceit?"
        },
        {
          "front": "And all for nothing!",
          "back": "For Hecuba!"
        },
        {
          "front": "What's Hecuba to him,",
          "back": "or he to Hecuba,"
        },
        {
          "front": "That he should weep",
          "back": "for her?"
        }
      ]
    },
    {
      "id": "but-soft-what-light",
      "title": "But soft, what light through yonder window breaks",
      "source": "Romeo and Juliet",
      "character": "Romeo",
      "act": "Act 2, Scene 2",
      "chunks": [
        {
          "front": "But soft, what light through",
          "back": "yonder window breaks?"
        },
        {
          "front": "It is the east,",
          "back": "and Juliet is the sun."
        },
        {
          "front": "Arise, fair sun,",
          "back": "and kill the envious moon,"
        },
        {
          "front": "Who is already sick",
          "back": "and pale with grief,"
        },
        {
          "front": "That thou, her maid, art",
          "back": "far more fair than she."
        },
        {
          "front": "Be not her maid, since",
          "back": "she is envious;"
        },
        {
          "front": "Her vestal livery is but",
          "back": "sick and green,"
        },
        {
          "front": "And none but fools",
          "back": "do wear it; cast it off."
        },
        {
          "front": "It is my lady,",
          "back": "O, it is my love!"
        },
        {
          "front": "O, that she knew",
          "back": "she were!"
        }
      ]
    },
    {
      "id": "o-romeo-romeo",
      "title": "O Romeo, Romeo, wherefore art thou Romeo",
      "source": "Romeo and Juliet",
      "character": "Juliet",
      "act": "Act 2, Scene 2",
      "chunks": [
        {
          "front": "O Romeo, Romeo,",
          "back": "wherefore art thou Romeo?"
        },
        {
          "front": "Deny thy father and",
          "back": "refuse thy name;"
        },
        {
          "front": "Or, if thou wilt not,",
          "back": "be but sworn my love,"
        },
        {
          "front": "And I'll no longer be",
          "back": "a Capulet."
        },
        {
          "front": "'Tis but thy name",
          "back": "that is my enemy;"
        },
        {
          "front": "Thou art thyself, though",
          "back": "not a Montague."
        },
        {
          "front": "What's Montague? It is",
          "back": "nor hand, nor foot,"
        },
        {
          "front": "Nor arm, nor face, nor",
          "back": "any other part"
        },
        {
          "front": "Belonging to a man.",
          "back": "O, be some other name!"
        },
        {
          "front": "What's in a name? That which we call",
          "back": "a rose"
        },
        {
          "front": "By any other name would",
          "back": "smell as sweet."
        }
      ]
    },
    {
      "id": "quality-of-mercy",
      "title": "The quality of mercy is not strained",
      "source": "The Merchant of Venice",
      "character": "Portia",
      "act": "Act 4, Scene 1",
      "chunks": [
        {
          "front": "The quality of mercy is",
          "back": "not strained;"
        },
        {
          "front": "It droppeth as the gentle rain",
          "back": "from heaven"
        },
        {
          "front": "Upon the place beneath.",
          "back": "It is twice blest:"
        },
        {
          "front": "It blesseth him that gives",
          "back": "and him that takes."
        },
        {
          "front": "'Tis mightiest in the mightiest;",
          "back": "it becomes"
        },
        {
          "front": "The thronèd monarch better",
          "back": "than his crown."
        },
        {
          "front": "His sceptre shows the force",
          "back": "of temporal power,"
        },
        {
          "front": "The attribute to awe",
          "back": "and majesty,"
        },
        {
          "front": "Wherein doth sit the dread",
          "back": "and fear of kings;"
        },
        {
          "front": "But mercy is above",
          "back": "this sceptred sway."
        },
        {
          "front": "It is enthronèd in the hearts",
          "back": "of kings,"
        },
        {
          "front": "It is an attribute to",
          "back": "God himself;"
        },
        {
          "front": "And earthly power doth then",
          "back": "show likest God's"
        },
        {
          "front": "When mercy seasons",
          "back": "justice."
        },
        {
          "front": "Therefore, Jew, though justice",
          "back": "be thy plea,"
        },
        {
          "front": "Consider this: that in the course",
          "back": "of justice,"
        },
        {
          "front": "None of us should see",
          "back": "salvation."
        },
        {
          "front": "We do pray for mercy, and that same prayer",
          "back": "doth teach us all"
        },
        {
          "front": "to render the deeds",
          "back": "of mercy."
        }
      ]
    },
    {
      "id": "if-music-be-the-food",
      "title": "If music be the food of love",
      "source": "Twelfth Night",
      "character": "Orsino",
      "act": "Act 1, Scene 1",
      "chunks": [
        {
          "front": "If music be the food",
          "back": "of love, play on;"
        },
        {
          "front": "Give me excess of it,",
          "back": "that, surfeiting,"
        },
        {
          "front": "The appetite may sicken,",
          "back": "and so die."
        },
        {
          "front": "That strain again!",
          "back": "it had a dying fall;"
        },
        {
          "front": "O, it came o'er my ear",
          "back": "like the sweet sound"
        },
        {
          "front": "That breathes upon",
          "back": "a bank of violets,"
        },
        {
          "front": "Stealing and",
          "back": "giving odour!"
        },
        {
          "front": "Enough; no more:",
          "back": "'Tis not so sweet now as it was before."
        }
      ]
    },
    {
      "id": "friends-romans-countrymen",
      "title": "Friends, Romans, countrymen",
      "source": "Julius Caesar",
      "character": "Mark Antony",
      "act": "Act 3, Scene 2",
      "chunks": [
        {
          "front": "Friends, Romans, countrymen,",
          "back": "lend me your ears;"
        },
        {
          "front": "I come to bury Caesar,",
          "back": "not to praise him."
        },
        {
          "front": "The evil that men do",
          "back": "lives after them;"
        },
        {
          "front": "The good is oft",
          "back": "interrèd with their bones;"
        },
        {
          "front": "So let it be",
          "back": "with Caesar."
        },
        {
          "front": "The noble Brutus hath told you",
          "back": "Caesar was ambitious:"
        },
        {
          "front": "If it were so, it was",
          "back": "a grievous fault,"
        },
        {
          "front": "And grievously hath",
          "back": "Caesar answer'd it."
        },
        {
          "front": "Here, under leave of Brutus",
          "back": "and the rest—"
        },
        {
          "front": "For Brutus is an",
          "back": "honourable man;"
        },
        {
          "front": "So are they all, all",
          "back": "honourable men—"
        },
        {
          "front": "Come I to speak in",
          "back": "Caesar's funeral."
        },
        {
          "front": "He was my friend, faithful",
          "back": "and just to me:"
        },
        {
          "front": "But Brutus says he was ambitious;",
          "back": "And Brutus is an honourable man."
        },
        {
          "front": "He hath brought many captives",
          "back": "home to Rome,"
        },
        {
          "front": "Whose ransoms did the general",
          "back": "coffers fill:"
        },
        {
          "front": "Did this in Caesar",
          "back": "seem ambitious?"
        },
        {
          "front": "When that the poor have cried,",
          "back": "Caesar hath wept:"
        },
        {
          "front": "Ambition should be made",
          "back": "of sterner stuff:"
        },
        {
          "front": "Yet Brutus says he was ambitious;",
          "back": "And Brutus is an honourable man."
        },
        {
          "front": "You all did see that on the Lupercal",
          "back": "I thrice presented him a kingly crown,"
        },
        {
          "front": "Which he did thrice refuse:",
          "back": "was this ambition?"
        },
        {
          "front": "Yet Brutus says he was ambitious;",
          "back": "And, sure, he is an honourable man."
        },
        {
          "front": "I speak not to disprove",
          "back": "what Brutus spoke,"
        },
        {
          "front": "But here I am to speak",
          "back": "what I do know."
        },
        {
          "front": "You all did love him once,",
          "back": "not without cause:"
        },
        {
          "front": "What cause withholds you then,",
          "back": "to mourn for him?"
        },
        {
          "front": "O judgment! thou art fled",
          "back": "to brutish beasts,"
        },
        {
          "front": "And men have lost",
          "back": "their reason."
        },
        {
          "front": "Bear with me; my heart is in",
          "back": "the coffin there with Caesar,"
        },
        {
          "front": "And I must pause till it",
          "back": "come back to me."
        }
      ]
    },
    {
      "id": "blow-winds",
      "title": "Blow, winds, and crack your cheeks",
      "source": "King Lear",
      "character": "King Lear",
      "act": "Act 3, Scene 2",
      "chunks": [
        {
          "front": "Blow, winds, and",
          "back": "crack your cheeks! rage! blow!"
        },
        {
          "front": "You cataracts and hurricanoes,",
          "back": "spout"
        },
        {
          "front": "Till you have drench'd",
          "back": "our steeples, drown'd the cocks!"
        },
        {
          "front": "You sulph'rous and thought-executing fires,",
          "back": "Vaunt-couriers to oak-cleaving thunderbolts,"
        },
        {
          "front": "Singe my",
          "back": "white head!"
        },
        {
          "front": "And thou, all-shaking thunder,",
          "back": "Smite flat the thick rotundity o' the world!"
        },
        {
          "front": "Crack nature's moulds,",
          "back": "all germens spill at once,"
        },
        {
          "front": "That make",
          "back": "ingrateful man!"
        }
      ]
    },
    {
      "id": "our-revels-now-are-ended",
      "title": "Our revels now are ended",
      "source": "The Tempest",
      "character": "Prospero",
      "act": "Act 4, Scene 1",
      "chunks": [
        {
          "front": "Our revels now",
          "back": "are ended."
        },
        {
          "front": "These our actors, as I foretold you,",
          "back": "Were all spirits, and"
        },
        {
          "front": "Are melted into air,",
          "back": "into thin air:"
        },
        {
          "front": "And, like the baseless fabric",
          "back": "of this vision,"
        },
        {
          "front": "The cloud-capp'd towers,",
          "back": "the gorgeous palaces,"
        },
        {
          "front": "The solemn temples,",
          "back": "the great globe itself,"
        },
        {
          "front": "Yea, all which it inherit,",
          "back": "shall dissolve,"
        },
        {
          "front": "And, like this insubstantial pageant faded,",
          "back": "Leave not a rack behind."
        },
        {
          "front": "We are such stuff as",
          "back": "dreams are made on;"
        },
        {
          "front": "And our little life is",
          "back": "rounded with a sleep."
        }
      ]
    },
    {
      "id": "o-that-this-too-solid-flesh",
      "title": "O, that this too, too solid flesh would melt",
      "source": "Hamlet",
      "character": "Hamlet",
      "act": "Act 1, Scene 2",
      "chunks": [
        {
          "front": "O, that this too, too solid flesh",
          "back": "would melt,"
        },
        {
          "front": "Thaw, and resolve itself",
          "back": "into a dew!"
        },
        {
          "front": "Or that the Everlasting had not fix'd",
          "back": "His canon 'gainst self-slaughter!"
        },
        {
          "front": "O God! God!",
          "back": "How weary, stale, flat, and unprofitable"
        },
        {
          "front": "Seem to me all the uses",
          "back": "of this world!"
        },
        {
          "front": "Fie on't! ah, fie!",
          "back": "'tis an unweeded garden,"
        },
        {
          "front": "That grows to seed; things rank",
          "back": "and gross in nature"
        },
        {
          "front": "Possess it merely.",
          "back": "That it should come to this!"
        }
      ]
    },
    {
      "id": "what-a-piece-of-work",
      "title": "What a piece of work is a man",
      "source": "Hamlet",
      "character": "Hamlet",
      "act": "Act 2, Scene 2",
      "chunks": [
        {
          "front": "What a piece of work",
          "back": "is a man!"
        },
        {
          "front": "How noble in reason!",
          "back": "how infinite in faculty!"
        },
        {
          "front": "in form and moving how express",
          "back": "and admirable!"
        },
        {
          "front": "in action",
          "back": "how like an angel!"
        },
        {
          "front": "in apprehension",
          "back": "how like a god!"
        },
        {
          "front": "the beauty of the world!",
          "back": "the paragon of animals!"
        },
        {
          "front": "And yet, to me, what is",
          "back": "this quintessence of dust?"
        },
        {
          "front": "Man delights not me:",
          "back": "no, nor woman neither."
        }
      ]
    },
    {
      "id": "out-damned-spot",
      "title": "Out, damned spot",
      "source": "Macbeth",
      "character": "Lady Macbeth",
      "act": "Act 5, Scene 1",
      "chunks": [
        {
          "front": "Out, damned spot!",
          "back": "out, I say!"
        },
        {
          "front": "One: two: why, then",
          "back": "'tis time to do't."
        },
        {
          "front": "Hell is murky!",
          "back": "Fie, my lord, fie!"
        },
        {
          "front": "A soldier,",
          "back": "and afeard?"
        },
        {
          "front": "What need we fear who knows it,",
          "back": "when none can call our power to account?"
        },
        {
          "front": "Yet who would have thought",
          "back": "the old man to have had so much blood in him?"
        },
        {
          "front": "Here's the smell of the blood still:",
          "back": "all the perfumes of Arabia"
        },
        {
          "front": "will not sweeten",
          "back": "this little hand."
        },
        {
          "front": "Oh, oh, oh!",
          "back": "What's done cannot be undone."
        }
      ]
    },
    {
      "id": "we-few-we-happy-few",
      "title": "We few, we happy few",
      "source": "Henry V",
      "character": "King Henry",
      "act": "Act 4, Scene 3",
      "chunks": [
        {
          "front": "We few, we happy few,",
          "back": "we band of brothers;"
        },
        {
          "front": "For he to-day that",
          "back": "sheds his blood with me"
        },
        {
          "front": "Shall be",
          "back": "my brother;"
        },
        {
          "front": "be he ne'er so vile,",
          "back": "This day shall gentle his condition:"
        },
        {
          "front": "And gentlemen in England",
          "back": "now a-bed"
        },
        {
          "front": "Shall think themselves accurs'd",
          "back": "they were not here,"
        },
        {
          "front": "And hold their manhoods cheap",
          "back": "whiles any speaks"
        },
        {
          "front": "That fought with us upon",
          "back": "Saint Crispin's day."
        }
      ]
    },
    {
      "id": "to-thine-own-self",
      "title": "To thine own self be true",
      "source": "Hamlet",
      "character": "Polonius",
      "act": "Act 1, Scene 3",
      "chunks": [
        {
          "front": "Give every man thy ear,",
          "back": "but few thy voice;"
        },
        {
          "front": "Take each man's censure,",
          "back": "but reserve thy judgment."
        },
        {
          "front": "Costly thy habit",
          "back": "as thy purse can buy,"
        },
        {
          "front": "But not express'd in fancy;",
          "back": "rich, not gaudy;"
        },
        {
          "front": "For the apparel oft",
          "back": "proclaims the man."
        },
        {
          "front": "Neither a borrower",
          "back": "nor a lender be;"
        },
        {
          "front": "For loan oft loses",
          "back": "both itself and friend,"
        },
        {
          "front": "And borrowing dulls the edge",
          "back": "of husbandry."
        },
        {
          "front": "This above all:",
          "back": "to thine own self be true,"
        },
        {
          "front": "And it must follow, as the night the day,",
          "back": "Thou canst not then be false to any man."
        }
      ]
    },
    {
      "id": "full-fathom-five",
      "title": "Full fathom five thy father lies",
      "source": "The Tempest",
      "character": "Ariel",
      "act": "Act 1, Scene 2",
      "chunks": [
        {
          "front": "Full fathom five",
          "back": "thy father lies;"
        },
        {
          "front": "Of his bones are",
          "back": "coral made;"
        },
        {
          "front": "Those are pearls",
          "back": "that were his eyes:"
        },
        {
          "front": "Nothing of him",
          "back": "that doth fade,"
        },
        {
          "front": "But doth suffer",
          "back": "a sea-change"
        },
        {
          "front": "Into something rich",
          "back": "and strange."
        },
        {
          "front": "Sea-nymphs hourly",
          "back": "ring his knell:"
        },
        {
          "front": "Ding-dong.",
          "back": "Hark! now I hear them—"
        },
        {
          "front": "Ding-dong,",
          "back": "bell."
        }
      ]
    },
    {
      "id": "be-not-afeard",
      "title": "Be not afeard; the isle is full of noises",
      "source": "The Tempest",
      "character": "Caliban",
      "act": "Act 3, Scene 2",
      "chunks": [
        {
          "front": "Be not afeard; the isle is",
          "back": "full of noises,"
        },
        {
          "front": "Sounds and sweet airs,",
          "back": "that give delight and hurt not."
        },
        {
          "front": "Sometimes a thousand",
          "back": "twangling instruments"
        },
        {
          "front": "Will hum about",
          "back": "mine ears;"
        },
        {
          "front": "and sometime voices",
          "back": "That, if I then had waked after long sleep,"
        },
        {
          "front": "Will make me sleep again:",
          "back": "and then, in dreaming,"
        },
        {
          "front": "The clouds methought would open",
          "back": "and show riches"
        },
        {
          "front": "Ready to drop upon me,",
          "back": "that, when I waked,"
        },
        {
          "front": "I cried to dream",
          "back": "again."
        }
      ]
    },
    {
      "id": "how-all-occasions",
      "title": "How all occasions do inform against me",
      "source": "Hamlet",
      "character": "Hamlet",
      "act": "Act 4, Scene 4",
      "chunks": [
        {
          "front": "How all occasions do",
          "back": "inform against me,"
        },
        {
          "front": "And spur my dull",
          "back": "revenge!"
        },
        {
          "front": "What is a man, if his chief good",
          "back": "and market of his time"
        },
        {
          "front": "Be but to sleep",
          "back": "and feed? a beast, no more."
        },
        {
          "front": "Sure, he that made us with",
          "back": "such large discourse,"
        },
        {
          "front": "Looking before and after,",
          "back": "gave us not"
        },
        {
          "front": "That capability and",
          "back": "god-like reason"
        },
        {
          "front": "To fust in us",
          "back": "unused."
        }
      ]
    },
    {
      "id": "gallop-apace",
      "title": "Gallop apace, you fiery-footed steeds",
      "source": "Romeo and Juliet",
      "character": "Juliet",
      "act": "Act 3, Scene 2",
      "chunks": [
        {
          "front": "Gallop apace, you",
          "back": "fiery-footed steeds,"
        },
        {
          "front": "Towards Phoebus'",
          "back": "lodging:"
        },
        {
          "front": "such a wagoner as Phaëthon",
          "back": "would whip you to the west,"
        },
        {
          "front": "And bring in",
          "back": "cloudy night immediately."
        },
        {
          "front": "Spread thy close curtain,",
          "back": "love-performing night,"
        },
        {
          "front": "That runaway's eyes",
          "back": "may wink,"
        },
        {
          "front": "and Romeo leap to",
          "back": "these arms,"
        },
        {
          "front": "Untalked of",
          "back": "and unseen."
        }
      ]
    },
    {
      "id": "double-double",
      "title": "Double, double toil and trouble",
      "source": "Macbeth",
      "character": "The Witches",
      "act": "Act 4, Scene 1",
      "chunks": [
        {
          "front": "Double, double",
          "back": "toil and trouble;"
        },
        {
          "front": "Fire burn,",
          "back": "and cauldron bubble."
        },
        {
          "front": "Fillet of a fenny snake,",
          "back": "In the cauldron boil and bake;"
        },
        {
          "front": "Eye of newt,",
          "back": "and toe of frog,"
        },
        {
          "front": "Wool of bat,",
          "back": "and tongue of dog,"
        },
        {
          "front": "Adder's fork,",
          "back": "and blind-worm's sting,"
        },
        {
          "front": "Lizard's leg,",
          "back": "and howlet's wing,"
        },
        {
          "front": "For a charm of powerful trouble,",
          "back": "Like a hell-broth boil and bubble."
        },
        {
          "front": "Double, double",
          "back": "toil and trouble;"
        },
        {
          "front": "Fire burn,",
          "back": "and cauldron bubble."
        }
      ]
    },
    {
      "id": "pericles-gower-prologue",
      "title": "To sing a song that old was sung",
      "source": "Pericles",
      "character": "Gower",
      "act": "Act 1, Prologue",
      "chunks": [
        {
          "front": "To sing a song",
          "back": "that old was sung,"
        },
        {
          "front": "From ashes ancient",
          "back": "Gower is come,"
        },
        {
          "front": "Assuming man's infirmities,",
          "back": "To glad your ear and please your eyes."
        },
        {
          "front": "It hath been sung at festivals,",
          "back": "On ember-eves and holy-ales;"
        },
        {
          "front": "And lords and ladies",
          "back": "in their lives"
        },
        {
          "front": "Have read it for",
          "back": "restoratives."
        },
        {
          "front": "The purchase is to make",
          "back": "men glorious,"
        },
        {
          "front": "Et bonum quo antiquius,",
          "back": "eo melius."
        },
        {
          "front": "If you, born in these latter times,",
          "back": "When wit's more ripe,"
        },
        {
          "front": "accept my rhymes, And that to hear",
          "back": "an old man sing"
        },
        {
          "front": "May to your wishes",
          "back": "pleasure bring,"
        },
        {
          "front": "I life would wish,",
          "back": "and that I might"
        },
        {
          "front": "Waste it for you",
          "back": "like taper-light."
        }
      ]
    },
    {
      "id": "pericles-marina-recognition",
      "title": "My name is Marina",
      "source": "Pericles",
      "character": "Marina",
      "act": "Act 5, Scene 1",
      "chunks": [
        {
          "front": "My name is Marina,",
          "back": "and my mother died"
        },
        {
          "front": "Even in the act",
          "back": "of birth, I was born."
        },
        {
          "front": "My father was a king,",
          "back": "and call'd Pericles."
        },
        {
          "front": "And being at sea",
          "back": "my mother died,"
        },
        {
          "front": "With sorrow never closing",
          "back": "either of her eyes."
        },
        {
          "front": "The gods did favor me,",
          "back": "and I was brought"
        },
        {
          "front": "To Tarsus,",
          "back": "where I was bred,"
        },
        {
          "front": "And there a wicked queen",
          "back": "did seek my life,"
        },
        {
          "front": "But fortune brought me",
          "back": "to another place,"
        },
        {
          "front": "Where I have lived",
          "back": "in sorrow and in woe,"
        },
        {
          "front": "Yet kept my virtue",
          "back": "pure and clean."
        }
      ]
    },
    {
      "id": "pericles-what-music",
      "title": "But what music?",
      "source": "Pericles",
      "character": "Pericles",
      "act": "Act 5, Scene 1",
      "chunks": [
        {
          "front": "But what music?",
          "back": "My Marina,"
        },
        {
          "front": "Tell him o'er point by point,",
          "back": "for yet he seems to doubt,"
        },
        {
          "front": "How sure you are",
          "back": "my daughter."
        },
        {
          "front": "But what music?",
          "back": "I am wild in my beholding."
        },
        {
          "front": "O heavens bless",
          "back": "my girl!"
        },
        {
          "front": "But hark, what music?",
          "back": "Tell me, Helicanus,"
        },
        {
          "front": "My Marina,",
          "back": "tell her o'er"
        },
        {
          "front": "Point by point,",
          "back": "for yet he seems to doubt."
        },
        {
          "front": "O, come hither,",
          "back": "thou that begett'st him that did thee beget;"
        },
        {
          "front": "Thou that wast born at sea,",
          "back": "buried at Tarsus,"
        },
        {
          "front": "And found at sea again.",
          "back": "O Helicanus,"
        },
        {
          "front": "Down on thy knees,",
          "back": "thank the holy gods as loud"
        },
        {
          "front": "As thunder threatens us:",
          "back": "this is Marina."
        }
      ]
    },
    {
      "id": "coriolanus-banishment",
      "title": "You common cry of curs!",
      "source": "Coriolanus",
      "character": "Coriolanus",
      "act": "Act 3, Scene 3",
      "chunks": [
        {
          "front": "You common cry",
          "back": "of curs!"
        },
        {
          "front": "whose breath I hate",
          "back": "As reek o' the rotten fens,"
        },
        {
          "front": "whose loves I prize",
          "back": "As the dead carcasses of unburied men"
        },
        {
          "front": "That do corrupt",
          "back": "my air,"
        },
        {
          "front": "I banish you!",
          "back": "And here remain with your uncertainty!"
        },
        {
          "front": "Let every feeble rumor",
          "back": "shake your hearts!"
        },
        {
          "front": "Your enemies, with nodding",
          "back": "of their plumes,"
        },
        {
          "front": "Fan you into despair!",
          "back": "Have the power still"
        },
        {
          "front": "To banish your defenders;",
          "back": "till at length"
        },
        {
          "front": "Your ignorance, which finds not",
          "back": "till it feels,"
        },
        {
          "front": "Making not reservation",
          "back": "of yourselves,"
        },
        {
          "front": "Still your own foes,",
          "back": "deliver you as most"
        },
        {
          "front": "Abated captives",
          "back": "to some nation"
        },
        {
          "front": "That won you",
          "back": "without blows!"
        },
        {
          "front": "Despising, for you,",
          "back": "the city,"
        },
        {
          "front": "Thus I turn my back:",
          "back": "There is a world elsewhere."
        }
      ]
    },
    {
      "id": "coriolanus-alone-like-dragon",
      "title": "Like a lonely dragon",
      "source": "Coriolanus",
      "character": "Coriolanus",
      "act": "Act 4, Scene 1",
      "chunks": [
        {
          "front": "Come, leave your tears:",
          "back": "a brief farewell."
        },
        {
          "front": "The beast with many heads",
          "back": "butts me away."
        },
        {
          "front": "Nay, mother, Where is",
          "back": "your ancient courage?"
        },
        {
          "front": "You were used to say",
          "back": "Extremity was the trier of spirits;"
        },
        {
          "front": "That common chances",
          "back": "common men could bear;"
        },
        {
          "front": "That when the sea was calm",
          "back": "all boats alike"
        },
        {
          "front": "Show'd mastership",
          "back": "in floating;"
        },
        {
          "front": "Fortune's blows, when most struck home,",
          "back": "being gentle wounded,"
        },
        {
          "front": "craves a noble",
          "back": "cunning."
        },
        {
          "front": "I go alone, Like to",
          "back": "a lonely dragon,"
        },
        {
          "front": "that his fen Makes fear'd",
          "back": "and talk'd of more than seen."
        }
      ]
    },
    {
      "id": "coriolanus-aufidius-welcome",
      "title": "My name is Caius Marcius",
      "source": "Coriolanus",
      "character": "Coriolanus",
      "act": "Act 4, Scene 5",
      "chunks": [
        {
          "front": "My name is",
          "back": "Caius Marcius,"
        },
        {
          "front": "who hath done to thee",
          "back": "particularly"
        },
        {
          "front": "and to all the Volsces",
          "back": "Great hurt and mischief;"
        },
        {
          "front": "thereto witness may",
          "back": "My surname, Coriolanus:"
        },
        {
          "front": "The painful service,",
          "back": "The extreme dangers"
        },
        {
          "front": "and the drops of blood",
          "back": "Shed for my thankless country"
        },
        {
          "front": "are requited But with",
          "back": "that surname;"
        },
        {
          "front": "a good memory, And witness",
          "back": "of the malice and displeasure"
        },
        {
          "front": "Which thou shouldst bear me:",
          "back": "only that name remains."
        },
        {
          "front": "The cruelty and envy",
          "back": "of the people,"
        },
        {
          "front": "Permitted by our dastard nobles,",
          "back": "who Have all forsook me,"
        },
        {
          "front": "hath devour'd the rest;",
          "back": "And suffer'd me by the voice of slaves"
        },
        {
          "front": "to be Whoop'd out",
          "back": "of Rome."
        }
      ]
    },
    {
      "id": "coriolanus-mother-bow",
      "title": "What is this? Your knees to me?",
      "source": "Coriolanus",
      "character": "Coriolanus",
      "act": "Act 5, Scene 3",
      "chunks": [
        {
          "front": "What is this?",
          "back": "Your knees to me?"
        },
        {
          "front": "to your corrected son?",
          "back": "Then let the pebbles"
        },
        {
          "front": "on the hungry beach",
          "back": "Fillip the stars;"
        },
        {
          "front": "then let the mutinous winds",
          "back": "Strike the proud cedars"
        },
        {
          "front": "'gainst the fiery sun;",
          "back": "Murdering impossibility,"
        },
        {
          "front": "to make What cannot be,",
          "back": "slight work."
        },
        {
          "front": "I beseech you, peace:",
          "back": "Or, if you'd ask,"
        },
        {
          "front": "remember this before:",
          "back": "The thing I have forsworn"
        },
        {
          "front": "to grant may never Be held",
          "back": "by you denials."
        },
        {
          "front": "Do not bid me dismiss",
          "back": "my soldiers,"
        },
        {
          "front": "or capitulate Again",
          "back": "with Rome's mechanics:"
        },
        {
          "front": "tell me not Wherein",
          "back": "I seem unnatural:"
        },
        {
          "front": "desire not To allay",
          "back": "my rages and revenges"
        },
        {
          "front": "with Your colder reasons.",
          "back": "O no more, no more!"
        }
      ]
    }
  ]
}